MANIFEST.in
RELEASE-VERSION
pavement.py
paver-minilib.zip
setup.py
version.py
arduino_scons/__init__.py
arduino_scons/arduino_build.py
arduino_scons/auto_config.py
arduino_scons/find_avrdude.py
arduino_scons/get_libs.py
arduino_scons/git_util.py
arduino_scons.egg-info/PKG-INFO
arduino_scons.egg-info/SOURCES.txt
arduino_scons.egg-info/dependency_links.txt
arduino_scons.egg-info/pbr.json
arduino_scons.egg-info/requires.txt
arduino_scons.egg-info/top_level.txt
arduino_scons/bin/windows/avr/bin/ld.exe
arduino_scons/bin/windows/bin/avr-ld.exe
arduino_scons/site_tools/__init__.py
arduino_scons/site_tools/disttar/__init__.py
arduino_scons/site_tools/disttar/disttar.py