Metadata-Version: 1.0
Name: arduino-scons
Version: 0.1.post9
Summary: SCons tools for building Arduino projects.
Home-page: http://github.com/wheeler-microfluidics/arduino_scons.git
Author: Christian Fobel
Author-email: christian@fobel.net
License: GPLv2
Platform: UNKNOWN
